doimbu/__init__.py
doimbu/__main__.py
doimbu/builder.py
doimbu/paths.py
doimbu/sources/__init__.py
doimbu/sources/dir_structure.py
doimbu/sources/file_config.py
doimbu/sources/git.py
doimbu/version.py
doimbu-0.7.0.dist-info/LICENSE
doimbu-0.7.0.dist-info/METADATA
doimbu-0.7.0.dist-info/WHEEL
doimbu-0.7.0.dist-info/RECORD
