Metadata-Version: 2.1
Name: doimbu
Version: 0.7.0
Summary: Lightweight tool for docker image creation with multiple variants.
Home-page: https://gitlab.com/alex-carvalho-dockeration/doimbu
License: MIT
Author: alex carvalho
Author-email: alex.carvalho.data@gmail.com
Requires-Python: >=3.12,<4.0
Classifier: Development Status :: 4 - Beta
Classifier: Environment :: Console
Classifier: Intended Audience :: Developers
Classifier: Intended Audience :: Information Technology
Classifier: Intended Audience :: System Administrators
Classifier: License :: OSI Approved :: MIT License
Classifier: Operating System :: OS Independent
Classifier: Programming Language :: Python :: 3
Classifier: Programming Language :: Python :: 3.12
Classifier: Programming Language :: Python :: 3.13
Classifier: Topic :: Software Development
Classifier: Topic :: Software Development :: Build Tools
Classifier: Topic :: Software Development :: Version Control :: Git
Requires-Dist: pydantic (>=2.10.1,<3.0.0)
Project-URL: Changelog, https://gitlab.com/alex-carvalho-dockeration/doimbu/-/blob/master/CHANGELOG.md
Project-URL: Issues, https://gitlab.com/alex-carvalho-dockeration/doimbu/-/issues
Project-URL: Repository, https://gitlab.com/alex-carvalho-dockeration/doimbu
